{
  "date": "2026-07-13",
  "updated_at": "2026-07-13T00:10:30Z",
  "lotteries": [
    {
      "id": "powerball",
      "country": "US",
      "state": "NATIONAL",
      "name": "Powerball",
      "date": "2026-07-11",
      "numbers": [
        8,
        10,
        14,
        45,
        59,
        5
      ],
      "extra": {
        "powerplay": "2"
      },
      "jackpot": {
        "amount": 457000000,
        "currency": "USD"
      },
      "source": "https://www.texaslottery.com/export/sites/lottery/Games/Powerball/index.html",
      "updated_at": "2026-07-13T00:10:30Z"
    },
    {
      "id": "megamillions",
      "country": "US",
      "state": "NATIONAL",
      "name": "Mega Millions",
      "date": "2026-07-10",
      "numbers": [
        2,
        39,
        44,
        46,
        56,
        23
      ],
      "extra": {
        "next_draw_date": "2026-07-14",
        "multipliers_available": "2X, 3X, 4X, 5X or 10X"
      },
      "jackpot": {
        "amount": 637000000,
        "currency": "USD"
      },
      "source": "https://www.texaslottery.com/export/sites/lottery/Games/Mega_Millions/index.html",
      "updated_at": "2026-07-13T00:10:31Z"
    }
  ]
}